{ "height":24,
 "infinite":false,
 "layers":[
        {
         "data":[1, 1, 1, 1, 1, 1, 1, 1, 1, 1, 1, 1, 1, 1, 1, 1, 1, 1, 1, 1, 1, 1, 1, 1, 1, 1, 1, 1, 1, 1, 1, 1, 1, 1, 1, 1, 1, 1, 1, 1, 1, 1, 1, 1, 1, 1, 1, 1, 1, 1, 1, 1, 1, 1, 1, 1, 1, 1, 1, 1, 1, 1, 1, 1, 1, 1, 1, 1, 1, 1, 1, 1, 1, 1, 1, 1, 1, 1, 1, 1, 1, 1, 1, 1, 1, 1, 1, 1, 1, 1, 1, 1, 1, 1, 1, 1, 1, 1, 1, 1, 1, 1, 1, 1, 1, 1, 1, 1, 1, 1, 1, 1, 1, 1, 1, 1, 1, 1, 1, 1, 1, 1, 1, 1, 1, 1, 1, 1, 1, 1, 1, 1, 1, 1, 1, 1, 1, 1, 1, 1, 1, 1, 1, 1, 1, 1, 1, 1, 1, 1, 1, 1, 1, 1, 1, 1, 1, 1, 1, 1, 1, 1, 1, 1, 1, 1, 1, 1, 1, 1, 1, 1, 1, 1, 1, 1, 1, 1, 1, 1, 1, 1, 1, 1, 1, 1, 1, 1, 1, 1, 1, 1, 1, 1, 1, 1, 1, 1, 1, 1, 1, 1, 1, 1, 1, 1, 1, 1, 1, 1, 1, 1, 1, 1, 1, 1, 1, 1, 1, 1, 1, 1, 1, 1, 1, 1, 1, 1, 1, 1, 1, 1, 1, 1, 1, 1, 1, 1, 1, 1, 1, 1, 1, 1, 1, 1, 1, 1, 1, 1, 1, 1, 1, 1, 1, 1, 1, 1, 1, 1, 1, 1, 1, 1, 1, 1, 1, 1, 1, 1, 1, 1, 1, 1, 1, 1, 1, 1, 1, 1, 1, 1, 1, 1, 1, 1, 1, 1, 1, 1, 1, 1, 1, 1, 1, 1, 1, 1, 1, 1, 1, 1, 1, 1, 1, 1, 1, 1, 1, 1, 1, 1, 1, 1, 1, 1, 1, 1, 1, 1, 1, 1, 1, 1, 1, 1, 1, 1, 1, 1, 1, 1, 1, 1, 1, 1, 1, 1, 1, 1, 1, 1, 1, 1, 1, 1, 1, 1, 1, 1, 1, 1, 1, 1, 1, 1, 1, 1, 1, 1, 1, 1, 1, 1, 1, 1, 1, 1, 1, 1, 1, 1, 1, 1, 1, 1, 1, 1, 1, 1, 1, 1, 1, 1, 1, 1, 1, 1, 1, 1, 1, 1, 1, 1, 1, 1, 1, 1, 1, 1, 1, 1, 1, 1, 1, 1, 1, 1, 1, 1, 1, 1, 1, 1, 1, 1, 1, 1, 1, 1, 1, 1, 1, 1, 1, 1, 1, 1, 1, 1, 1, 1, 1, 1, 1, 1, 1, 1, 1, 1, 1, 1, 1, 1, 1, 1, 1, 1, 1, 1, 1, 1, 1, 1, 1, 1, 1, 1, 1, 1, 1, 1, 1, 1, 1, 1, 1, 1, 1, 1, 1, 1, 1, 1, 1, 1, 1, 1, 1, 1, 1, 1, 1, 1, 1, 1, 1, 1, 1, 1, 1, 1, 1, 1, 1, 1, 1, 1, 1, 1, 1, 1, 1, 1, 1, 1, 1, 1, 1, 1, 1, 1, 1, 1, 1, 1, 1, 1, 1, 1, 1, 1, 1, 1, 1, 1, 1, 1, 1, 1, 1, 1, 1, 1, 1, 1, 1, 1, 1, 1, 1, 1, 1, 1, 1, 1, 1, 1, 1, 1, 1, 1, 1, 1, 1, 1, 1, 1, 1, 1, 1, 1, 1, 1, 1, 1, 1, 1, 1, 1, 1, 1, 1, 1, 1, 1, 1, 1, 1, 1, 1, 1, 1, 1, 1, 1, 1, 1, 1, 1, 1, 1, 1, 1, 1, 1, 1, 1, 1, 1, 1, 1, 1, 1, 1, 1, 1, 1, 1, 1, 1, 1, 1, 1, 1, 1, 1, 1, 1, 1, 1, 1, 1, 1, 1, 1, 1, 1, 1, 1, 1, 1, 1, 1, 1, 1, 1, 1, 1, 1, 1, 1, 1, 1, 1, 1, 1, 1, 1, 1, 1, 1, 1, 1, 1, 1, 1, 1, 1, 1, 1, 1, 1, 1, 1, 1, 1, 1, 1, 1, 1, 1, 1, 1, 1, 1, 1, 1, 1, 1, 1, 1, 1, 1, 1, 1, 1, 1, 1, 1, 1, 1, 1, 1, 1, 1, 1, 1, 1, 1, 1, 1, 1, 1, 1, 1, 1, 1, 1, 1, 1, 1, 1, 1, 1, 1, 1, 1, 1, 1, 1, 1, 1, 1, 1, 1, 1, 1, 1, 1, 1, 1, 1, 1, 1, 1, 1, 1, 1, 1, 1, 1, 1, 1, 1, 1, 1, 1, 1, 1, 1, 1, 1, 1, 1, 1, 1, 1, 1, 1, 1, 1, 1, 1, 1, 1, 1, 1, 1, 1, 1, 1, 1, 1, 1, 1, 1, 1, 1, 1, 1, 1, 1, 1, 1, 1, 1, 1, 1, 1, 1, 1, 1, 1, 1, 1, 1, 1, 1, 1, 1, 1, 1, 1, 1, 1, 1, 1, 1, 1, 1, 1, 1, 1, 1, 1, 1, 1, 1, 1, 1, 1, 1, 1, 1, 1, 1, 1, 1, 1, 1, 1, 1, 1, 1, 1, 1, 1, 1, 1, 1, 1, 1, 1, 1, 1, 1, 1, 1, 1, 1, 1, 1, 1, 1, 1, 1, 1, 1, 1, 1, 1, 1, 1, 1, 1, 1, 1, 1, 1, 1, 1, 1, 1, 1, 1, 1, 1, 1, 1, 1, 1, 1, 1, 1, 1, 1, 1, 1, 1, 1, 1, 1, 1, 1, 1, 1, 1, 1, 1, 1, 1, 1, 1, 1, 1, 1, 1, 1, 1, 1, 1, 1, 1, 1, 1, 1, 1, 1, 1, 1, 1, 1, 1, 1, 1, 1, 1, 1, 1, 1, 1, 1, 1, 1, 1, 1, 1, 1, 1, 1, 1, 1, 1, 1, 1, 1, 1, 1, 1, 1, 1, 1, 1, 1, 1, 1, 1, 1, 1],
         "height":24,
         "name":"floor",
         "opacity":1,
         "type":"tilelayer",
         "visible":true,
         "width":40,
         "x":0,
         "y":0
        }, 
        {
         "data":[0, 0, 0, 0, 0, 0, 0, 0, 0, 0, 0, 0, 0, 0, 0, 0, 0, 0, 0, 0, 0, 0, 0, 0, 0, 0, 0, 0, 0, 0, 0, 0, 0, 0, 0, 0, 0, 0, 0, 0, 0, 0, 0, 0, 0, 0, 0, 0, 0, 0, 0, 394, 0, 0, 0, 0, 0, 0, 0, 0, 0, 0, 0, 0, 0, 0, 0, 0, 0, 0, 0, 0, 0, 0, 0, 0, 0, 0, 0, 0, 0, 0, 0, 0, 0, 0, 0, 0, 0, 0, 0, 0, 0, 0, 0, 0, 0, 0, 0, 0, 0, 0, 0, 0, 0, 0, 0, 0, 0, 0, 0, 0, 0, 0, 0, 0, 0, 0, 0, 0, 0, 0, 0, 393, 0, 0, 0, 0, 0, 0, 0, 0, 0, 0, 0, 0, 0, 0, 0, 0, 0, 0, 0, 0, 0, 0, 0, 0, 0, 0, 0, 0, 0, 0, 0, 0, 0, 0, 0, 0, 0, 0, 0, 0, 0, 0, 0, 0, 0, 0, 268, 0, 0, 0, 0, 0, 0, 0, 0, 0, 0, 0, 266, 0, 0, 0, 0, 0, 0, 0, 0, 0, 0, 0, 0, 0, 267, 0, 0, 0, 0, 0, 0, 0, 0, 0, 0, 0, 0, 0, 0, 0, 0, 0, 0, 0, 0, 0, 0, 0, 0, 0, 0, 0, 0, 0, 0, 0, 0, 0, 0, 0, 0, 0, 0, 0, 0, 0, 0, 0, 0, 0, 0, 0, 0, 0, 0, 0, 0, 0, 0, 0, 0, 0, 0, 0, 0, 2147484042, 0, 0, 0, 0, 0, 0, 2147484041, 0, 0, 0, 0, 0, 0, 0, 0, 0, 0, 0, 0, 0, 0, 0, 0, 0, 0, 0, 0, 0, 0, 0, 0, 0, 0, 0, 0, 0, 0, 0, 0, 0, 0, 0, 0, 0, 0, 0, 0, 0, 0, 0, 0, 0, 0, 0, 0, 0, 0, 0, 0, 0, 0, 0, 0, 0, 0, 0, 0, 0, 0, 0, 0, 0, 0, 0, 0, 0, 0, 0, 0, 0, 0, 0, 0, 0, 0, 0, 0, 0, 0, 0, 0, 0, 0, 0, 0, 0, 0, 0, 0, 0, 0, 0, 0, 0, 0, 0, 0, 0, 0, 0, 0, 0, 0, 0, 0, 0, 0, 0, 0, 0, 0, 0, 0, 0, 0, 0, 0, 0, 0, 0, 0, 0, 0, 0, 0, 0, 0, 0, 0, 0, 0, 0, 0, 0, 0, 0, 0, 0, 0, 0, 0, 0, 0, 0, 0, 0, 0, 0, 0, 0, 0, 0, 0, 0, 0, 0, 0, 0, 0, 0, 0, 0, 0, 0, 0, 0, 0, 0, 0, 0, 0, 0, 0, 0, 0, 0, 0, 0, 0, 0, 0, 0, 0, 0, 2147483915, 0, 0, 0, 0, 0, 0, 0, 0, 0, 0, 0, 0, 0, 0, 394, 0, 0, 0, 0, 0, 0, 0, 0, 0, 0, 0, 0, 0, 0, 0, 0, 0, 0, 0, 0, 0, 0, 0, 0, 0, 0, 0, 0, 0, 0, 0, 0, 0, 0, 0, 0, 0, 0, 0, 0, 0, 0, 0, 0, 0, 0, 0, 0, 0, 0, 0, 2147484042, 0, 0, 0, 265, 0, 0, 0, 0, 0, 0, 0, 0, 0, 0, 0, 0, 0, 0, 0, 0, 0, 0, 0, 0, 0, 0, 0, 0, 0, 0, 0, 0, 0, 0, 0, 0, 0, 0, 0, 0, 0, 0, 0, 0, 0, 0, 0, 0, 0, 0, 0, 0, 0, 0, 0, 0, 0, 0, 0, 0, 0, 0, 0, 0, 0, 0, 0, 0, 0, 0, 0, 0, 0, 0, 0, 0, 0, 0, 0, 0, 0, 0, 0, 0, 0, 0, 0, 0, 0, 0, 0, 0, 0, 0, 0, 0, 0, 0, 0, 0, 0, 0, 0, 0, 0, 0, 0, 0, 0, 0, 0, 0, 0, 0, 0, 0, 0, 0, 0, 0, 0, 0, 0, 0, 0, 0, 0, 0, 0, 0, 0, 0, 0, 0, 0, 0, 0, 0, 0, 0, 0, 0, 0, 0, 0, 0, 0, 0, 0, 0, 0, 0, 0, 0, 0, 0, 0, 0, 0, 0, 0, 0, 0, 0, 0, 0, 0, 0, 0, 0, 0, 0, 0, 0, 0, 0, 0, 0, 0, 0, 0, 0, 0, 0, 0, 0, 0, 0, 0, 0, 0, 0, 0, 0, 0, 0, 0, 0, 0, 0, 0, 0, 0, 0, 0, 0, 0, 0, 0, 0, 0, 0, 0, 0, 0, 0, 0, 0, 0, 0, 0, 0, 0, 0, 0, 0, 0, 0, 0, 0, 0, 0, 0, 0, 0, 0, 0, 0, 0, 0, 0, 0, 0, 0, 0, 0, 0, 0, 0, 0, 0, 0, 0, 0, 0, 0, 0, 0, 0, 0, 0, 0, 0, 0, 0, 0, 0, 2147483914, 0, 0, 0, 0, 0, 0, 0, 0, 265, 0, 0, 0, 0, 0, 0, 0, 0, 0, 0, 0, 0, 0, 0, 0, 0, 0, 0, 0, 0, 0, 0, 0, 0, 0, 0, 0, 0, 0, 0, 0, 0, 0, 0, 0, 0, 0, 0, 0, 0, 0, 0, 0, 0, 2147484041, 0, 0, 0, 0, 0, 0, 0, 0, 0, 0, 268, 0, 0, 0, 0, 0, 0, 0, 0, 0, 0, 0, 0, 0, 0, 0, 0, 393, 0, 0, 0, 0, 0, 0, 0, 0, 0, 0, 0, 0, 0, 0, 0, 0, 0, 0, 0, 0, 0, 0, 0, 0, 0, 0, 0, 0, 0, 0, 0, 0, 0, 0, 0, 0, 0, 0, 0, 0, 0, 0, 0, 0, 0, 0, 0, 0, 0, 0, 0, 0, 0, 0, 0, 0, 0, 0, 0, 0, 0, 0, 0, 0, 0, 0, 0, 0, 0, 0, 0, 0, 0, 0, 0, 0, 0, 0, 0, 0, 0, 0, 0, 0, 0, 0, 0, 0, 0, 0],
         "height":24,
         "name":"floor_decor",
         "opacity":1,
         "type":"tilelayer",
         "visible":true,
         "width":40,
         "x":0,
         "y":0
        }, 
        {
         "data":[1035, 1035, 1035, 1035, 1035, 1035, 1035, 1035, 1035, 1035, 1035, 1035, 1035, 1035, 1035, 1035, 1035, 1035, 1035, 1035, 1035, 1035, 1035, 1035, 1035, 1035, 1035, 1035, 1035, 1035, 1035, 1035, 1035, 1035, 1035, 1035, 1035, 1035, 1035, 1035, 1163, 1163, 1163, 1163, 1163, 1163, 1163, 1163, 1163, 1163, 1163, 1163, 1163, 1163, 1163, 1163, 1163, 1163, 1035, 1035, 1035, 1163, 1163, 1163, 1163, 1163, 1163, 1163, 1163, 1163, 1163, 1163, 1163, 1163, 1163, 1163, 1163, 1163, 1035, 1035, 0, 0, 0, 0, 0, 0, 0, 0, 0, 0, 0, 0, 0, 0, 0, 0, 0, 0, 1034, 1035, 1036, 0, 0, 0, 0, 0, 0, 0, 0, 0, 0, 0, 0, 0, 0, 0, 0, 0, 1034, 1035, 0, 0, 0, 0, 0, 0, 0, 0, 0, 0, 0, 0, 0, 0, 0, 0, 0, 0, 1034, 1035, 1036, 0, 0, 0, 0, 0, 0, 0, 0, 0, 0, 0, 0, 0, 0, 0, 0, 0, 1034, 1035, 0, 0, 0, 0, 0, 0, 0, 0, 0, 0, 0, 0, 0, 0, 0, 0, 0, 0, 1034, 1035, 1036, 0, 0, 0, 0, 0, 0, 0, 0, 0, 0, 0, 0, 0, 0, 0, 0, 0, 1034, 1035, 0, 0, 0, 0, 0, 0, 0, 0, 0, 0, 0, 0, 0, 0, 0, 0, 0, 0, 1034, 1035, 1036, 0, 0, 0, 0, 0, 0, 0, 0, 0, 0, 0, 0, 0, 0, 0, 0, 0, 1034, 1035, 907, 907, 907, 907, 907, 907, 907, 907, 907, 907, 907, 907, 907, 907, 907, 908, 0, 0, 1034, 1035, 1035, 907, 907, 907, 907, 907, 907, 907, 907, 907, 907, 907, 907, 907, 907, 907, 0, 0, 1034, 1035, 1035, 1035, 1035, 1035, 1035, 1035, 1035, 1035, 1035, 1035, 1035, 1035, 1035, 1035, 1035, 1036, 0, 0, 1034, 1035, 1035, 1035, 1035, 1035, 1035, 1035, 1035, 1035, 1035, 1035, 1035, 1035, 1035, 1035, 1035, 1035, 0, 0, 1034, 1035, 1035, 1035, 1035, 1035, 1035, 1035, 1035, 1035, 1035, 1035, 1035, 1035, 1035, 1035, 1035, 1036, 0, 0, 1034, 1035, 1035, 1035, 1035, 1035, 1035, 1035, 1035, 1035, 1035, 1035, 1035, 1035, 1035, 1035, 1035, 1035, 0, 0, 1034, 1035, 1163, 1163, 1163, 1163, 1163, 1163, 1163, 1163, 1163, 1163, 1163, 1163, 1163, 1163, 1035, 1036, 0, 0, 1162, 1163, 1163, 1163, 1163, 1163, 1163, 1163, 1163, 1163, 1163, 1163, 1163, 1163, 1163, 1163, 1035, 1036, 0, 0, 1162, 1163, 0, 0, 0, 0, 0, 0, 0, 0, 0, 0, 0, 0, 0, 0, 1034, 1036, 0, 0, 0, 0, 0, 0, 0, 0, 0, 0, 0, 0, 0, 0, 0, 0, 0, 0, 1034, 1036, 0, 0, 0, 0, 0, 0, 0, 0, 0, 0, 0, 0, 0, 0, 0, 0, 0, 0, 1034, 1036, 0, 0, 0, 0, 0, 0, 0, 0, 0, 0, 0, 0, 0, 0, 0, 0, 0, 0, 1034, 1036, 0, 0, 0, 0, 0, 0, 0, 0, 0, 0, 0, 0, 0, 0, 0, 0, 0, 0, 1034, 1036, 0, 0, 0, 0, 0, 0, 0, 0, 0, 0, 0, 0, 0, 0, 0, 0, 0, 0, 1034, 1036, 0, 0, 0, 0, 0, 0, 0, 0, 0, 0, 0, 0, 0, 0, 0, 0, 0, 0, 1034, 1036, 0, 0, 0, 0, 0, 0, 0, 0, 0, 0, 0, 0, 0, 0, 0, 0, 0, 0, 1034, 1036, 0, 0, 0, 0, 907, 907, 907, 908, 0, 0, 0, 0, 906, 907, 907, 907, 907, 907, 1035, 1035, 907, 907, 907, 907, 907, 907, 907, 908, 0, 0, 0, 0, 906, 907, 907, 907, 907, 907, 1035, 1035, 907, 907, 907, 907, 1035, 1035, 1035, 1036, 0, 0, 0, 0, 1034, 1035, 1035, 1035, 1035, 1035, 1035, 1035, 1035, 1035, 1035, 1035, 1035, 1035, 1035, 1036, 0, 0, 0, 0, 1034, 1035, 1035, 1035, 1163, 1163, 1163, 1163, 1163, 1163, 1035, 1035, 1035, 1035, 1035, 1036, 0, 0, 0, 0, 1034, 1035, 1035, 1035, 1035, 1035, 1035, 1035, 1035, 1035, 1035, 1035, 1035, 1035, 1035, 1036, 0, 0, 0, 0, 1034, 1035, 1035, 1036, 0, 0, 0, 0, 0, 0, 1034, 1035, 1163, 1163, 1163, 1164, 0, 0, 0, 0, 1034, 1035, 1035, 1035, 1163, 1163, 1163, 1163, 1163, 1163, 1035, 1035, 1163, 1163, 1163, 1164, 0, 0, 0, 0, 1034, 1035, 1035, 1036, 0, 0, 0, 0, 0, 0, 1034, 1035, 0, 0, 0, 0, 0, 0, 0, 0, 1034, 1035, 1035, 1036, 0, 0, 0, 0, 0, 0, 1034, 1036, 0, 0, 0, 0, 0, 0, 0, 0, 1034, 1035, 1035, 1036, 0, 0, 0, 0, 0, 0, 1034, 1035, 0, 0, 0, 0, 0, 0, 0, 0, 1034, 1035, 1035, 1036, 0, 0, 0, 0, 0, 0, 1034, 1036, 0, 0, 0, 0, 0, 0, 0, 0, 1034, 1035, 1035, 1036, 0, 0, 0, 0, 0, 0, 1034, 1035, 0, 0, 0, 0, 0, 0, 0, 0, 1034, 1035, 1035, 1036, 0, 0, 0, 0, 0, 0, 1034, 1036, 0, 0, 0, 0, 0, 0, 0, 0, 1034, 1035, 1035, 1036, 0, 0, 0, 0, 0, 0, 1034, 1035, 0, 0, 0, 0, 0, 0, 0, 0, 1034, 1035, 1035, 1036, 0, 0, 0, 0, 0, 0, 1034, 1036, 0, 0, 0, 0, 0, 0, 0, 0, 1034, 1035, 1035, 1036, 0, 0, 0, 0, 0, 0, 1034, 1035, 907, 908, 0, 0, 906, 908, 0, 0, 1034, 1035, 1035, 1036, 0, 0, 906, 908, 0, 0, 1034, 1035, 907, 908, 0, 0, 906, 908, 0, 0, 1034, 1035, 1035, 1036, 0, 0, 906, 908, 0, 0, 1034, 1035, 1035, 1036, 0, 0, 1034, 1036, 0, 0, 1034, 1035, 1035, 1036, 0, 0, 1034, 1036, 0, 0, 1034, 1035, 1035, 1036, 0, 0, 1034, 1036, 0, 0, 1034, 1035, 1035, 1036, 0, 0, 1035, 1036, 0, 0, 1034, 1035],
         "height":24,
         "name":"walls",
         "opacity":1,
         "type":"tilelayer",
         "visible":true,
         "width":40,
         "x":0,
         "y":0
        }, 
        {
         "data":[0, 0, 0, 0, 0, 0, 0, 0, 0, 0, 0, 0, 0, 0, 0, 0, 0, 0, 0, 0, 0, 0, 0, 0, 0, 0, 0, 0, 0, 0, 0, 0, 0, 0, 0, 0, 0, 0, 0, 0, 0, 0, 0, 0, 0, 0, 0, 0, 0, 0, 0, 0, 0, 0, 0, 0, 0, 0, 0, 0, 0, 0, 0, 0, 0, 0, 0, 0, 0, 0, 0, 0, 0, 0, 0, 0, 0, 0, 0, 0, 0, 0, 0, 0, 0, 0, 0, 0, 0, 0, 0, 0, 0, 0, 0, 0, 0, 0, 0, 0, 0, 0, 0, 0, 0, 0, 0, 0, 0, 0, 0, 0, 0, 0, 0, 0, 0, 0, 0, 0, 0, 0, 0, 0, 0, 0, 0, 0, 0, 0, 0, 0, 0, 0, 0, 0, 0, 0, 0, 0, 0, 0, 0, 0, 0, 0, 0, 0, 0, 0, 0, 0, 0, 0, 0, 0, 0, 0, 0, 0, 0, 0, 0, 0, 0, 0, 0, 0, 0, 0, 0, 0, 0, 0, 0, 0, 0, 0, 0, 0, 0, 0, 0, 0, 0, 0, 0, 0, 0, 0, 0, 0, 0, 0, 0, 0, 0, 0, 0, 0, 0, 0, 0, 0, 0, 0, 0, 0, 0, 0, 0, 0, 0, 0, 0, 0, 0, 0, 0, 0, 0, 0, 0, 0, 0, 0, 0, 0, 0, 0, 0, 0, 0, 0, 0, 0, 0, 0, 0, 0, 0, 0, 0, 0, 0, 0, 0, 0, 0, 0, 0, 0, 0, 0, 0, 0, 0, 0, 0, 0, 0, 0, 0, 0, 0, 0, 0, 0, 0, 0, 0, 0, 0, 0, 0, 0, 0, 0, 0, 0, 0, 0, 0, 0, 0, 0, 0, 0, 0, 0, 0, 0, 0, 0, 0, 0, 0, 0, 0, 0, 0, 0, 0, 0, 0, 0, 0, 0, 0, 0, 0, 0, 0, 0, 0, 0, 0, 0, 0, 0, 0, 0, 0, 0, 0, 0, 0, 0, 0, 0, 0, 0, 0, 0, 0, 0, 0, 0, 0, 0, 0, 0, 0, 0, 0, 0, 0, 0, 0, 0, 0, 0, 0, 0, 0, 0, 0, 0, 0, 0, 0, 0, 0, 0, 0, 0, 0, 0, 0, 0, 0, 0, 0, 0, 0, 0, 0, 0, 0, 0, 0, 0, 0, 0, 0, 0, 0, 0, 0, 0, 0, 0, 0, 0, 0, 0, 0, 0, 0, 0, 0, 0, 0, 0, 0, 0, 0, 0, 0, 0, 0, 0, 0, 0, 0, 0, 0, 0, 0, 0, 0, 0, 0, 0, 0, 0, 0, 0, 0, 0, 0, 0, 0, 0, 0, 0, 0, 0, 0, 0, 0, 0, 0, 0, 0, 0, 0, 0, 0, 0, 0, 0, 0, 0, 0, 0, 0, 0, 0, 0, 0, 0, 0, 0, 0, 0, 0, 0, 0, 0, 0, 0, 0, 0, 0, 0, 0, 0, 0, 0, 0, 0, 0, 0, 0, 0, 0, 0, 0, 0, 0, 0, 0, 0, 0, 0, 0, 0, 0, 0, 0, 0, 0, 0, 0, 0, 0, 0, 0, 0, 0, 0, 0, 0, 0, 0, 0, 0, 0, 0, 0, 0, 0, 0, 0, 0, 0, 0, 0, 0, 0, 0, 0, 0, 0, 0, 0, 0, 0, 0, 0, 0, 0, 0, 0, 0, 0, 0, 0, 0, 0, 0, 0, 0, 0, 0, 0, 0, 0, 0, 0, 0, 0, 0, 0, 0, 0, 0, 0, 0, 0, 0, 0, 0, 0, 0, 0, 0, 0, 0, 0, 0, 0, 0, 0, 0, 0, 0, 0, 0, 0, 0, 0, 0, 0, 0, 0, 0, 0, 0, 0, 0, 0, 0, 0, 0, 0, 0, 0, 0, 0, 0, 0, 0, 0, 0, 0, 0, 0, 0, 0, 0, 0, 0, 0, 0, 0, 0, 0, 0, 0, 0, 0, 0, 0, 0, 0, 0, 0, 0, 0, 0, 0, 0, 0, 0, 0, 0, 0, 0, 0, 0, 0, 0, 0, 0, 0, 0, 0, 0, 0, 0, 0, 0, 0, 0, 0, 0, 0, 0, 0, 0, 0, 0, 0, 0, 0, 0, 0, 0, 0, 0, 0, 0, 0, 0, 0, 0, 0, 0, 0, 0, 0, 0, 0, 0, 0, 0, 0, 0, 0, 0, 0, 0, 0, 0, 0, 0, 0, 0, 0, 0, 0, 0, 0, 0, 0, 0, 0, 0, 0, 0, 0, 0, 0, 0, 0, 0, 0, 0, 0, 0, 0, 0, 0, 0, 0, 0, 0, 0, 0, 0, 0, 0, 0, 0, 0, 0, 0, 0, 0, 0, 0, 0, 0, 0, 0, 0, 0, 0, 0, 0, 0, 0, 0, 0, 0, 0, 0, 0, 0, 0, 0, 0, 0, 0, 0, 0, 0, 0, 0, 0, 0, 0, 0, 0, 0, 0, 0, 0, 0, 0, 0, 0, 0, 0, 0, 0, 0, 0, 0, 0, 0, 0, 0, 0, 0, 0, 0, 0, 0, 0, 0, 0, 0, 0, 0, 0, 0, 0, 0, 0, 0, 0, 0, 0, 0, 0, 0, 0, 0, 0, 0, 0, 0, 0, 0, 0, 0, 0, 0, 0, 0, 0, 0, 0, 0, 0, 0, 0, 0, 0, 0, 0, 0, 0, 0, 0, 0, 0, 0, 0, 0, 0, 0, 0, 0, 0, 0, 0, 0, 0, 0, 0, 0, 0, 0, 0, 0, 0, 0, 0, 0, 0, 0, 0, 0, 0, 0, 0, 0, 0, 0, 0, 0, 0, 0, 0, 0, 0, 0, 0, 0, 0, 0, 0, 0, 0, 0, 0, 0, 0, 0, 0, 0, 0, 0, 0, 0, 0, 0, 0, 0, 0, 0, 0, 0, 0, 0, 0, 0, 0, 0, 0, 0, 0, 0, 0, 0, 0, 0, 0, 0, 0, 0, 0, 0, 0, 0, 0, 0, 0, 0, 0, 0, 0, 0, 0, 0, 0],
         "height":24,
         "name":"walls_decor",
         "opacity":1,
         "type":"tilelayer",
         "visible":true,
         "width":40,
         "x":0,
         "y":0
        }],
 "nextobjectid":3,
 "orientation":"orthogonal",
 "renderorder":"right-down",
 "tiledversion":"1.1.5",
 "tileheight":16,
 "tilesets":[
        {
         "columns":128,
         "firstgid":1,
         "image":"..\/images\/map_tileset.png",
         "imageheight":2175,
         "imagewidth":2175,
         "margin":0,
         "name":"map_tileset",
         "spacing":1,
         "tilecount":16384,
         "tileheight":16,
         "tileproperties":
            {
             "10":
                {
                 "collides":true
                },
             "1024":
                {
                 "collides":true
                },
             "1025":
                {
                 "collides":true
                },
             "1026":
                {
                 "collides":true
                },
             "1030":
                {
                 "collides":true
                },
             "1031":
                {
                 "collides":true
                },
             "1032":
                {
                 "collides":true
                },
             "1033":
                {
                 "collides":true
                },
             "1034":
                {
                 "collides":true
                },
             "1035":
                {
                 "collides":true
                },
             "1036":
                {
                 "collides":true
                },
             "1037":
                {
                 "collides":true
                },
             "1038":
                {
                 "collides":true
                },
             "1039":
                {
                 "collides":true
                },
             "1040":
                {
                 "collides":true
                },
             "1041":
                {
                 "collides":true
                },
             "1042":
                {
                 "collides":true
                },
             "1043":
                {
                 "collides":true
                },
             "1044":
                {
                 "collides":true
                },
             "1045":
                {
                 "collides":true
                },
             "1046":
                {
                 "collides":true
                },
             "1047":
                {
                 "collides":true
                },
             "11":
                {
                 "collides":true
                },
             "1152":
                {
                 "collides":true
                },
             "1153":
                {
                 "collides":true
                },
             "1158":
                {
                 "collides":true
                },
             "1159":
                {
                 "collides":true
                },
             "1160":
                {
                 "collides":true
                },
             "1161":
                {
                 "collides":true
                },
             "1162":
                {
                 "collides":true
                },
             "1163":
                {
                 "collides":true
                },
             "1164":
                {
                 "collides":true
                },
             "1165":
                {
                 "collides":true
                },
             "1166":
                {
                 "collides":true
                },
             "1167":
                {
                 "collides":true
                },
             "1168":
                {
                 "collides":true
                },
             "1169":
                {
                 "collides":true
                },
             "1170":
                {
                 "collides":true
                },
             "1171":
                {
                 "collides":true
                },
             "1172":
                {
                 "collides":true
                },
             "1173":
                {
                 "collides":true
                },
             "1174":
                {
                 "collides":true
                },
             "1175":
                {
                 "collides":true
                },
             "1280":
                {
                 "collides":true
                },
             "1281":
                {
                 "collides":true
                },
             "1282":
                {
                 "collides":true
                },
             "1283":
                {
                 "collides":true
                },
             "1284":
                {
                 "collides":true
                },
             "1285":
                {
                 "collides":true
                },
             "1286":
                {
                 "collides":true
                },
             "1287":
                {
                 "collides":true
                },
             "1288":
                {
                 "collides":true
                },
             "1289":
                {
                 "collides":true
                },
             "1290":
                {
                 "collides":true
                },
             "1291":
                {
                 "collides":true
                },
             "1292":
                {
                 "collides":true
                },
             "1293":
                {
                 "collides":true
                },
             "1294":
                {
                 "collides":true
                },
             "1295":
                {
                 "collides":true
                },
             "1296":
                {
                 "collides":true
                },
             "1297":
                {
                 "collides":true
                },
             "1298":
                {
                 "collides":true
                },
             "1299":
                {
                 "collides":true
                },
             "1300":
                {
                 "collides":true
                },
             "1301":
                {
                 "collides":true
                },
             "1302":
                {
                 "collides":true
                },
             "1303":
                {
                 "collides":true
                },
             "131":
                {
                 "collides":true
                },
             "132":
                {
                 "collides":true
                },
             "133":
                {
                 "collides":true
                },
             "134":
                {
                 "collides":true
                },
             "135":
                {
                 "collides":true
                },
             "136":
                {
                 "collides":true
                },
             "137":
                {
                 "collides":true
                },
             "138":
                {
                 "collides":true
                },
             "139":
                {
                 "collides":true
                },
             "140":
                {
                 "collides":true
                },
             "1408":
                {
                 "collides":true
                },
             "1409":
                {
                 "collides":true
                },
             "141":
                {
                 "collides":true
                },
             "1410":
                {
                 "collides":true
                },
             "1411":
                {
                 "collides":true
                },
             "1412":
                {
                 "collides":true
                },
             "1413":
                {
                 "collides":true
                },
             "1414":
                {
                 "collides":true
                },
             "1415":
                {
                 "collides":true
                },
             "1416":
                {
                 "collides":true
                },
             "1417":
                {
                 "collides":true
                },
             "1418":
                {
                 "collides":true
                },
             "1419":
                {
                 "collides":true
                },
             "142":
                {
                 "collides":true
                },
             "1420":
                {
                 "collides":true
                },
             "1421":
                {
                 "collides":true
                },
             "1422":
                {
                 "collides":true
                },
             "1423":
                {
                 "collides":true
                },
             "1424":
                {
                 "collides":true
                },
             "1425":
                {
                 "collides":true
                },
             "1426":
                {
                 "collides":true
                },
             "1427":
                {
                 "collides":true
                },
             "1428":
                {
                 "collides":true
                },
             "1429":
                {
                 "collides":true
                },
             "143":
                {
                 "collides":true
                },
             "1430":
                {
                 "collides":true
                },
             "1431":
                {
                 "collides":true
                },
             "144":
                {
                 "collides":true
                },
             "145":
                {
                 "collides":true
                },
             "146":
                {
                 "collides":true
                },
             "147":
                {
                 "collides":true
                },
             "148":
                {
                 "collides":true
                },
             "149":
                {
                 "collides":true
                },
             "150":
                {
                 "collides":true
                },
             "151":
                {
                 "collides":true
                },
             "1536":
                {
                 "collides":true
                },
             "1537":
                {
                 "collides":true
                },
             "1538":
                {
                 "collides":true
                },
             "1542":
                {
                 "collides":true
                },
             "1543":
                {
                 "collides":true
                },
             "1544":
                {
                 "collides":true
                },
             "1545":
                {
                 "collides":true
                },
             "1546":
                {
                 "collides":true
                },
             "1547":
                {
                 "collides":true
                },
             "1548":
                {
                 "collides":true
                },
             "1549":
                {
                 "collides":true
                },
             "1550":
                {
                 "collides":true
                },
             "1551":
                {
                 "collides":true
                },
             "1552":
                {
                 "collides":true
                },
             "1553":
                {
                 "collides":true
                },
             "1554":
                {
                 "collides":true
                },
             "1555":
                {
                 "collides":true
                },
             "1556":
                {
                 "collides":true
                },
             "1557":
                {
                 "collides":true
                },
             "1558":
                {
                 "collides":true
                },
             "1559":
                {
                 "collides":true
                },
             "1664":
                {
                 "collides":true
                },
             "1665":
                {
                 "collides":true
                },
             "256":
                {
                 "collides":true
                },
             "257":
                {
                 "collides":true
                },
             "258":
                {
                 "collides":true
                },
             "259":
                {
                 "collides":true
                },
             "260":
                {
                 "collides":true
                },
             "261":
                {
                 "collides":true
                },
             "262":
                {
                 "collides":true
                },
             "263":
                {
                 "collides":true
                },
             "268":
                {
                 "collides":true
                },
             "269":
                {
                 "collides":true
                },
             "270":
                {
                 "collides":true
                },
             "271":
                {
                 "collides":true
                },
             "272":
                {
                 "collides":true
                },
             "273":
                {
                 "collides":true
                },
             "274":
                {
                 "collides":true
                },
             "275":
                {
                 "collides":true
                },
             "276":
                {
                 "collides":true
                },
             "277":
                {
                 "collides":true
                },
             "278":
                {
                 "collides":true
                },
             "279":
                {
                 "collides":true
                },
             "384":
                {
                 "collides":true
                },
             "385":
                {
                 "collides":true
                },
             "386":
                {
                 "collides":true
                },
             "387":
                {
                 "collides":true
                },
             "388":
                {
                 "collides":true
                },
             "389":
                {
                 "collides":true
                },
             "396":
                {
                 "collides":true
                },
             "397":
                {
                 "collides":true
                },
             "398":
                {
                 "collides":true
                },
             "399":
                {
                 "collides":true
                },
             "400":
                {
                 "collides":true
                },
             "401":
                {
                 "collides":true
                },
             "402":
                {
                 "collides":true
                },
             "403":
                {
                 "collides":true
                },
             "404":
                {
                 "collides":true
                },
             "405":
                {
                 "collides":true
                },
             "406":
                {
                 "collides":true
                },
             "407":
                {
                 "collides":true
                },
             "512":
                {
                 "collides":true
                },
             "513":
                {
                 "collides":true
                },
             "514":
                {
                 "collides":true
                },
             "524":
                {
                 "collides":true
                },
             "525":
                {
                 "collides":true
                },
             "526":
                {
                 "collides":true
                },
             "527":
                {
                 "collides":true
                },
             "528":
                {
                 "collides":true
                },
             "529":
                {
                 "collides":true
                },
             "530":
                {
                 "collides":true
                },
             "531":
                {
                 "collides":true
                },
             "532":
                {
                 "collides":true
                },
             "533":
                {
                 "collides":true
                },
             "534":
                {
                 "collides":true
                },
             "535":
                {
                 "collides":true
                },
             "6":
                {
                 "collides":true
                },
             "640":
                {
                 "collides":true
                },
             "641":
                {
                 "collides":true
                },
             "646":
                {
                 "collides":true
                },
             "647":
                {
                 "collides":true
                },
             "648":
                {
                 "collides":true
                },
             "649":
                {
                 "collides":true
                },
             "650":
                {
                 "collides":true
                },
             "651":
                {
                 "collides":true
                },
             "652":
                {
                 "collides":true
                },
             "653":
                {
                 "collides":true
                },
             "654":
                {
                 "collides":true
                },
             "655":
                {
                 "collides":true
                },
             "656":
                {
                 "collides":true
                },
             "657":
                {
                 "collides":true
                },
             "658":
                {
                 "collides":true
                },
             "659":
                {
                 "collides":true
                },
             "660":
                {
                 "collides":true
                },
             "661":
                {
                 "collides":true
                },
             "662":
                {
                 "collides":true
                },
             "663":
                {
                 "collides":true
                },
             "7":
                {
                 "collides":true
                },
             "768":
                {
                 "collides":true
                },
             "769":
                {
                 "collides":true
                },
             "770":
                {
                 "collides":true
                },
             "771":
                {
                 "collides":true
                },
             "772":
                {
                 "collides":true
                },
             "773":
                {
                 "collides":true
                },
             "774":
                {
                 "collides":true
                },
             "775":
                {
                 "collides":true
                },
             "776":
                {
                 "collides":true
                },
             "780":
                {
                 "collides":true
                },
             "781":
                {
                 "collides":true
                },
             "782":
                {
                 "collides":true
                },
             "783":
                {
                 "collides":true
                },
             "784":
                {
                 "collides":true
                },
             "785":
                {
                 "collides":true
                },
             "786":
                {
                 "collides":true
                },
             "787":
                {
                 "collides":true
                },
             "788":
                {
                 "collides":true
                },
             "789":
                {
                 "collides":true
                },
             "790":
                {
                 "collides":true
                },
             "791":
                {
                 "collides":true
                },
             "8":
                {
                 "collides":true
                },
             "896":
                {
                 "collides":true
                },
             "897":
                {
                 "collides":true
                },
             "898":
                {
                 "collides":true
                },
             "899":
                {
                 "collides":true
                },
             "9":
                {
                 "collides":true
                },
             "900":
                {
                 "collides":true
                },
             "901":
                {
                 "collides":true
                },
             "902":
                {
                 "collides":true
                },
             "903":
                {
                 "collides":true
                },
             "904":
                {
                 "collides":true
                },
             "905":
                {
                 "collides":true
                },
             "906":
                {
                 "collides":true
                },
             "907":
                {
                 "collides":true
                },
             "908":
                {
                 "collides":true
                },
             "909":
                {
                 "collides":true
                },
             "910":
                {
                 "collides":true
                },
             "911":
                {
                 "collides":true
                },
             "912":
                {
                 "collides":true
                },
             "913":
                {
                 "collides":true
                },
             "914":
                {
                 "collides":true
                },
             "915":
                {
                 "collides":true
                },
             "916":
                {
                 "collides":true
                },
             "917":
                {
                 "collides":true
                },
             "918":
                {
                 "collides":true
                },
             "919":
                {
                 "collides":true
                }
            },
         "tilepropertytypes":
            {
             "10":
                {
                 "collides":"bool"
                },
             "1024":
                {
                 "collides":"bool"
                },
             "1025":
                {
                 "collides":"bool"
                },
             "1026":
                {
                 "collides":"bool"
                },
             "1030":
                {
                 "collides":"bool"
                },
             "1031":
                {
                 "collides":"bool"
                },
             "1032":
                {
                 "collides":"bool"
                },
             "1033":
                {
                 "collides":"bool"
                },
             "1034":
                {
                 "collides":"bool"
                },
             "1035":
                {
                 "collides":"bool"
                },
             "1036":
                {
                 "collides":"bool"
                },
             "1037":
                {
                 "collides":"bool"
                },
             "1038":
                {
                 "collides":"bool"
                },
             "1039":
                {
                 "collides":"bool"
                },
             "1040":
                {
                 "collides":"bool"
                },
             "1041":
                {
                 "collides":"bool"
                },
             "1042":
                {
                 "collides":"bool"
                },
             "1043":
                {
                 "collides":"bool"
                },
             "1044":
                {
                 "collides":"bool"
                },
             "1045":
                {
                 "collides":"bool"
                },
             "1046":
                {
                 "collides":"bool"
                },
             "1047":
                {
                 "collides":"bool"
                },
             "11":
                {
                 "collides":"bool"
                },
             "1152":
                {
                 "collides":"bool"
                },
             "1153":
                {
                 "collides":"bool"
                },
             "1158":
                {
                 "collides":"bool"
                },
             "1159":
                {
                 "collides":"bool"
                },
             "1160":
                {
                 "collides":"bool"
                },
             "1161":
                {
                 "collides":"bool"
                },
             "1162":
                {
                 "collides":"bool"
                },
             "1163":
                {
                 "collides":"bool"
                },
             "1164":
                {
                 "collides":"bool"
                },
             "1165":
                {
                 "collides":"bool"
                },
             "1166":
                {
                 "collides":"bool"
                },
             "1167":
                {
                 "collides":"bool"
                },
             "1168":
                {
                 "collides":"bool"
                },
             "1169":
                {
                 "collides":"bool"
                },
             "1170":
                {
                 "collides":"bool"
                },
             "1171":
                {
                 "collides":"bool"
                },
             "1172":
                {
                 "collides":"bool"
                },
             "1173":
                {
                 "collides":"bool"
                },
             "1174":
                {
                 "collides":"bool"
                },
             "1175":
                {
                 "collides":"bool"
                },
             "1280":
                {
                 "collides":"bool"
                },
             "1281":
                {
                 "collides":"bool"
                },
             "1282":
                {
                 "collides":"bool"
                },
             "1283":
                {
                 "collides":"bool"
                },
             "1284":
                {
                 "collides":"bool"
                },
             "1285":
                {
                 "collides":"bool"
                },
             "1286":
                {
                 "collides":"bool"
                },
             "1287":
                {
                 "collides":"bool"
                },
             "1288":
                {
                 "collides":"bool"
                },
             "1289":
                {
                 "collides":"bool"
                },
             "1290":
                {
                 "collides":"bool"
                },
             "1291":
                {
                 "collides":"bool"
                },
             "1292":
                {
                 "collides":"bool"
                },
             "1293":
                {
                 "collides":"bool"
                },
             "1294":
                {
                 "collides":"bool"
                },
             "1295":
                {
                 "collides":"bool"
                },
             "1296":
                {
                 "collides":"bool"
                },
             "1297":
                {
                 "collides":"bool"
                },
             "1298":
                {
                 "collides":"bool"
                },
             "1299":
                {
                 "collides":"bool"
                },
             "1300":
                {
                 "collides":"bool"
                },
             "1301":
                {
                 "collides":"bool"
                },
             "1302":
                {
                 "collides":"bool"
                },
             "1303":
                {
                 "collides":"bool"
                },
             "131":
                {
                 "collides":"bool"
                },
             "132":
                {
                 "collides":"bool"
                },
             "133":
                {
                 "collides":"bool"
                },
             "134":
                {
                 "collides":"bool"
                },
             "135":
                {
                 "collides":"bool"
                },
             "136":
                {
                 "collides":"bool"
                },
             "137":
                {
                 "collides":"bool"
                },
             "138":
                {
                 "collides":"bool"
                },
             "139":
                {
                 "collides":"bool"
                },
             "140":
                {
                 "collides":"bool"
                },
             "1408":
                {
                 "collides":"bool"
                },
             "1409":
                {
                 "collides":"bool"
                },
             "141":
                {
                 "collides":"bool"
                },
             "1410":
                {
                 "collides":"bool"
                },
             "1411":
                {
                 "collides":"bool"
                },
             "1412":
                {
                 "collides":"bool"
                },
             "1413":
                {
                 "collides":"bool"
                },
             "1414":
                {
                 "collides":"bool"
                },
             "1415":
                {
                 "collides":"bool"
                },
             "1416":
                {
                 "collides":"bool"
                },
             "1417":
                {
                 "collides":"bool"
                },
             "1418":
                {
                 "collides":"bool"
                },
             "1419":
                {
                 "collides":"bool"
                },
             "142":
                {
                 "collides":"bool"
                },
             "1420":
                {
                 "collides":"bool"
                },
             "1421":
                {
                 "collides":"bool"
                },
             "1422":
                {
                 "collides":"bool"
                },
             "1423":
                {
                 "collides":"bool"
                },
             "1424":
                {
                 "collides":"bool"
                },
             "1425":
                {
                 "collides":"bool"
                },
             "1426":
                {
                 "collides":"bool"
                },
             "1427":
                {
                 "collides":"bool"
                },
             "1428":
                {
                 "collides":"bool"
                },
             "1429":
                {
                 "collides":"bool"
                },
             "143":
                {
                 "collides":"bool"
                },
             "1430":
                {
                 "collides":"bool"
                },
             "1431":
                {
                 "collides":"bool"
                },
             "144":
                {
                 "collides":"bool"
                },
             "145":
                {
                 "collides":"bool"
                },
             "146":
                {
                 "collides":"bool"
                },
             "147":
                {
                 "collides":"bool"
                },
             "148":
                {
                 "collides":"bool"
                },
             "149":
                {
                 "collides":"bool"
                },
             "150":
                {
                 "collides":"bool"
                },
             "151":
                {
                 "collides":"bool"
                },
             "1536":
                {
                 "collides":"bool"
                },
             "1537":
                {
                 "collides":"bool"
                },
             "1538":
                {
                 "collides":"bool"
                },
             "1542":
                {
                 "collides":"bool"
                },
             "1543":
                {
                 "collides":"bool"
                },
             "1544":
                {
                 "collides":"bool"
                },
             "1545":
                {
                 "collides":"bool"
                },
             "1546":
                {
                 "collides":"bool"
                },
             "1547":
                {
                 "collides":"bool"
                },
             "1548":
                {
                 "collides":"bool"
                },
             "1549":
                {
                 "collides":"bool"
                },
             "1550":
                {
                 "collides":"bool"
                },
             "1551":
                {
                 "collides":"bool"
                },
             "1552":
                {
                 "collides":"bool"
                },
             "1553":
                {
                 "collides":"bool"
                },
             "1554":
                {
                 "collides":"bool"
                },
             "1555":
                {
                 "collides":"bool"
                },
             "1556":
                {
                 "collides":"bool"
                },
             "1557":
                {
                 "collides":"bool"
                },
             "1558":
                {
                 "collides":"bool"
                },
             "1559":
                {
                 "collides":"bool"
                },
             "1664":
                {
                 "collides":"bool"
                },
             "1665":
                {
                 "collides":"bool"
                },
             "256":
                {
                 "collides":"bool"
                },
             "257":
                {
                 "collides":"bool"
                },
             "258":
                {
                 "collides":"bool"
                },
             "259":
                {
                 "collides":"bool"
                },
             "260":
                {
                 "collides":"bool"
                },
             "261":
                {
                 "collides":"bool"
                },
             "262":
                {
                 "collides":"bool"
                },
             "263":
                {
                 "collides":"bool"
                },
             "268":
                {
                 "collides":"bool"
                },
             "269":
                {
                 "collides":"bool"
                },
             "270":
                {
                 "collides":"bool"
                },
             "271":
                {
                 "collides":"bool"
                },
             "272":
                {
                 "collides":"bool"
                },
             "273":
                {
                 "collides":"bool"
                },
             "274":
                {
                 "collides":"bool"
                },
             "275":
                {
                 "collides":"bool"
                },
             "276":
                {
                 "collides":"bool"
                },
             "277":
                {
                 "collides":"bool"
                },
             "278":
                {
                 "collides":"bool"
                },
             "279":
                {
                 "collides":"bool"
                },
             "384":
                {
                 "collides":"bool"
                },
             "385":
                {
                 "collides":"bool"
                },
             "386":
                {
                 "collides":"bool"
                },
             "387":
                {
                 "collides":"bool"
                },
             "388":
                {
                 "collides":"bool"
                },
             "389":
                {
                 "collides":"bool"
                },
             "396":
                {
                 "collides":"bool"
                },
             "397":
                {
                 "collides":"bool"
                },
             "398":
                {
                 "collides":"bool"
                },
             "399":
                {
                 "collides":"bool"
                },
             "400":
                {
                 "collides":"bool"
                },
             "401":
                {
                 "collides":"bool"
                },
             "402":
                {
                 "collides":"bool"
                },
             "403":
                {
                 "collides":"bool"
                },
             "404":
                {
                 "collides":"bool"
                },
             "405":
                {
                 "collides":"bool"
                },
             "406":
                {
                 "collides":"bool"
                },
             "407":
                {
                 "collides":"bool"
                },
             "512":
                {
                 "collides":"bool"
                },
             "513":
                {
                 "collides":"bool"
                },
             "514":
                {
                 "collides":"bool"
                },
             "524":
                {
                 "collides":"bool"
                },
             "525":
                {
                 "collides":"bool"
                },
             "526":
                {
                 "collides":"bool"
                },
             "527":
                {
                 "collides":"bool"
                },
             "528":
                {
                 "collides":"bool"
                },
             "529":
                {
                 "collides":"bool"
                },
             "530":
                {
                 "collides":"bool"
                },
             "531":
                {
                 "collides":"bool"
                },
             "532":
                {
                 "collides":"bool"
                },
             "533":
                {
                 "collides":"bool"
                },
             "534":
                {
                 "collides":"bool"
                },
             "535":
                {
                 "collides":"bool"
                },
             "6":
                {
                 "collides":"bool"
                },
             "640":
                {
                 "collides":"bool"
                },
             "641":
                {
                 "collides":"bool"
                },
             "646":
                {
                 "collides":"bool"
                },
             "647":
                {
                 "collides":"bool"
                },
             "648":
                {
                 "collides":"bool"
                },
             "649":
                {
                 "collides":"bool"
                },
             "650":
                {
                 "collides":"bool"
                },
             "651":
                {
                 "collides":"bool"
                },
             "652":
                {
                 "collides":"bool"
                },
             "653":
                {
                 "collides":"bool"
                },
             "654":
                {
                 "collides":"bool"
                },
             "655":
                {
                 "collides":"bool"
                },
             "656":
                {
                 "collides":"bool"
                },
             "657":
                {
                 "collides":"bool"
                },
             "658":
                {
                 "collides":"bool"
                },
             "659":
                {
                 "collides":"bool"
                },
             "660":
                {
                 "collides":"bool"
                },
             "661":
                {
                 "collides":"bool"
                },
             "662":
                {
                 "collides":"bool"
                },
             "663":
                {
                 "collides":"bool"
                },
             "7":
                {
                 "collides":"bool"
                },
             "768":
                {
                 "collides":"bool"
                },
             "769":
                {
                 "collides":"bool"
                },
             "770":
                {
                 "collides":"bool"
                },
             "771":
                {
                 "collides":"bool"
                },
             "772":
                {
                 "collides":"bool"
                },
             "773":
                {
                 "collides":"bool"
                },
             "774":
                {
                 "collides":"bool"
                },
             "775":
                {
                 "collides":"bool"
                },
             "776":
                {
                 "collides":"bool"
                },
             "780":
                {
                 "collides":"bool"
                },
             "781":
                {
                 "collides":"bool"
                },
             "782":
                {
                 "collides":"bool"
                },
             "783":
                {
                 "collides":"bool"
                },
             "784":
                {
                 "collides":"bool"
                },
             "785":
                {
                 "collides":"bool"
                },
             "786":
                {
                 "collides":"bool"
                },
             "787":
                {
                 "collides":"bool"
                },
             "788":
                {
                 "collides":"bool"
                },
             "789":
                {
                 "collides":"bool"
                },
             "790":
                {
                 "collides":"bool"
                },
             "791":
                {
                 "collides":"bool"
                },
             "8":
                {
                 "collides":"bool"
                },
             "896":
                {
                 "collides":"bool"
                },
             "897":
                {
                 "collides":"bool"
                },
             "898":
                {
                 "collides":"bool"
                },
             "899":
                {
                 "collides":"bool"
                },
             "9":
                {
                 "collides":"bool"
                },
             "900":
                {
                 "collides":"bool"
                },
             "901":
                {
                 "collides":"bool"
                },
             "902":
                {
                 "collides":"bool"
                },
             "903":
                {
                 "collides":"bool"
                },
             "904":
                {
                 "collides":"bool"
                },
             "905":
                {
                 "collides":"bool"
                },
             "906":
                {
                 "collides":"bool"
                },
             "907":
                {
                 "collides":"bool"
                },
             "908":
                {
                 "collides":"bool"
                },
             "909":
                {
                 "collides":"bool"
                },
             "910":
                {
                 "collides":"bool"
                },
             "911":
                {
                 "collides":"bool"
                },
             "912":
                {
                 "collides":"bool"
                },
             "913":
                {
                 "collides":"bool"
                },
             "914":
                {
                 "collides":"bool"
                },
             "915":
                {
                 "collides":"bool"
                },
             "916":
                {
                 "collides":"bool"
                },
             "917":
                {
                 "collides":"bool"
                },
             "918":
                {
                 "collides":"bool"
                },
             "919":
                {
                 "collides":"bool"
                }
            },
         "tilewidth":16,
         "transparentcolor":"#000000"
        }],
 "tilewidth":16,
 "type":"map",
 "version":1,
 "width":40
}